{
  "languageserver": {
    "bash": {
      "command": "bash-language-server",
      "args": ["start"],
      "filetypes": ["sh"],
      "ignoredRootPaths": ["~"]
    },
    "efm": {
      "command": "efm-langserver",
      "args": [],
      "filetypes": ["vim", "eruby", "markdown"]
    },
    "elmLS": {
      "command": "elm-language-server",
      "args": ["--stdio"],
      "filetypes": ["elm"],
      "rootPatterns": ["elm.json"],
      "initializationOptions": {
        "runtime": "node",
        "elmPath": "elm",
        "elmFormatPath": "elm-format",
        "elmTestPath": "./node_modules/elm-test/bin/elm-test"
      }
    }
  },
  "coc.preferences.enableFloatHighlight": false
}
